FileTree/FileTree.py
FileTree/__init__.py
file_tree_ds-1.0.6.dist-info/LICENSE
file_tree_ds-1.0.6.dist-info/METADATA
file_tree_ds-1.0.6.dist-info/WHEEL
file_tree_ds-1.0.6.dist-info/top_level.txt
file_tree_ds-1.0.6.dist-info/RECORD
