Metadata-Version: 2.1
Name: file-tree-ds
Version: 1.0.6
Summary: A tool to help create directories for data science project
Home-page: https://github.com/particlemontecarlo/FileTree
Author: Lawrence M
Author-email: lm3263658@gmail.com
Project-URL: Bug Tracker, https://github.com/particlemontecarlo/FileTree/issues
Classifier: Programming Language :: Python :: 3
Classifier: License :: OSI Approved :: MIT License
Classifier: Operating System :: OS Independent
Requires-Python: >=3.6
License-File: LICENSE
Requires-Dist: treelib (==1.6.1)
